LICENSE.rst
MANIFEST.in
README.md
setup.cfg
setup.py
docs/tutorials/ch3.pdb
docs/tutorials/ethane.mol2
docs/tutorials/methane.mol2
mbuild/__init__.py
mbuild/atb_client.py
mbuild/bond_graph.py
mbuild/box.py
mbuild/coarse_graining.py
mbuild/compound.py
mbuild/conversion.py
mbuild/coordinate_transform.py
mbuild/exceptions.py
mbuild/lattice.py
mbuild/packing.py
mbuild/pattern.py
mbuild/periodic_kdtree.py
mbuild/port.py
mbuild/version.py
mbuild.egg-info/PKG-INFO
mbuild.egg-info/SOURCES.txt
mbuild.egg-info/dependency_links.txt
mbuild.egg-info/entry_points.txt
mbuild.egg-info/not-zip-safe
mbuild.egg-info/top_level.txt
mbuild/formats/__init__.py
mbuild/formats/cassandramcf.py
mbuild/formats/compound_pb2.py
mbuild/formats/gsdwriter.py
mbuild/formats/hoomd_simulation.py
mbuild/formats/hoomd_snapshot.py
mbuild/formats/hoomdxml.py
mbuild/formats/json_formats.py
mbuild/formats/lammpsdata.py
mbuild/formats/par_writer.py
mbuild/formats/protobuf.py
mbuild/formats/vasp.py
mbuild/formats/xyz.py
mbuild/lib/__init__.py
mbuild/lib/atoms/__init__.py
mbuild/lib/atoms/c3.py
mbuild/lib/atoms/h.py
mbuild/lib/atoms/n4.py
mbuild/lib/bulk_materials/__init__.py
mbuild/lib/bulk_materials/amorphous_silica_bulk.pdb
mbuild/lib/bulk_materials/amorphous_silica_bulk.py
mbuild/lib/moieties/__init__.py
mbuild/lib/moieties/ch2.pdb
mbuild/lib/moieties/ch2.py
mbuild/lib/moieties/ch3.pdb
mbuild/lib/moieties/ch3.py
mbuild/lib/moieties/ester.pdb
mbuild/lib/moieties/ester.py
mbuild/lib/moieties/h2o.py
mbuild/lib/moieties/peg.py
mbuild/lib/moieties/peg_monomer.pdb
mbuild/lib/moieties/silane.pdb
mbuild/lib/moieties/silane.py
mbuild/lib/molecules/__init__.py
mbuild/lib/molecules/ethane.py
mbuild/lib/molecules/methane.py
mbuild/lib/recipes/__init__.py
mbuild/lib/recipes/alkane.py
mbuild/lib/recipes/monolayer.py
mbuild/lib/recipes/polymer.py
mbuild/lib/recipes/silica_interface.py
mbuild/lib/recipes/tiled_compound.py
mbuild/lib/surfaces/__init__.py
mbuild/lib/surfaces/amorphous_silica_sr1.0.pdb
mbuild/lib/surfaces/amorphous_silica_surface.py
mbuild/lib/surfaces/beta-cristobalite-expanded.mol2
mbuild/lib/surfaces/betacristobalite.py
mbuild/recipes/__init__.py
mbuild/tests/__init__.py
