Metadata-Version: 1.1
Name: mbuild
Version: 0.10.9
Summary: ['mBuild: A hierarchical, component based molecule builder', '', 'With just a few lines of mBuild code, you can assemble reusable components into', 'complex molecular systems for molecular dynamics simulations. mBuild is', 'designed to minimize or even eliminate the need to explicitly translate and', 'orient components when building systems: you simply tell it to connect two', "pieces! mBuild also keeps track of the system's topology so you don't have to", 'worry about manually defining
Home-page: https://github.com/mosdef-hub/mbuild
Author: Janos Sallai, Christoph Klein
Author-email: janos.sallai@vanderbilt.edu, christoph.klein@vanderbilt.edu
License: MIT
Download-URL: https://github.com/mosdef-hub/mbuild/tarball/0.10.9
Keywords: mbuild
Platform: UNKNOWN
Classifier: Development Status :: 4 - Beta
Classifier: Intended Audience :: Science/Research
Classifier: Intended Audience :: Developers
Classifier: License :: OSI Approved :: MIT License
Classifier: Natural Language :: English
Classifier: Programming Language :: Python
Classifier: Programming Language :: Python :: 3
Classifier: Topic :: Scientific/Engineering :: Chemistry
Classifier: Operating System :: Microsoft :: Windows
Classifier: Operating System :: POSIX
Classifier: Operating System :: Unix
Classifier: Operating System :: MacOS
